alone/MetaSingleton.py
alone/__init__.py
alone-0.1.7.dist-info/LICENSE
alone-0.1.7.dist-info/METADATA
alone-0.1.7.dist-info/WHEEL
alone-0.1.7.dist-info/top_level.txt
alone-0.1.7.dist-info/RECORD
