Metadata-Version: 2.1
Name: alone
Version: 0.1.7
Summary: Metaclass that defines a class as a singleton
Home-page: https://github.com/AdrienHorgnies/py-singleton
Author: Adrien Horgnies
Author-email: adrien.pierre.horgnies@gmail.com
License: MIT License
Download-URL: https://github.com/AdrienHorgnies/py-singleton/archive/0.1.7.tar.gz
Keywords: singleton
Platform: UNKNOWN
Classifier: Programming Language :: Python :: 3
Classifier: Programming Language :: Python :: 2
Classifier: License :: OSI Approved :: MIT License
Classifier: Operating System :: OS Independent
Classifier: Development Status :: 4 - Beta
Classifier: Intended Audience :: Developers
